shrub/__init__.py
shrub/common.py
shrub/mapping.py
shrub/network.py
shrub/onnx.py
shrub/predict.py
shrub/tflite.py
shrub/tvm.py
shrub/util.py
shrub-0.0.3.dist-info/LICENSE
shrub-0.0.3.dist-info/METADATA
shrub-0.0.3.dist-info/WHEEL
shrub-0.0.3.dist-info/top_level.txt
shrub-0.0.3.dist-info/RECORD
