Metadata-Version: 2.1
Name: shrub
Version: 0.0.3
Summary: Better Experience of Developping Deep Learning Systems
Home-page: https://jackwish.net/shrub
Author: 王振华（Zhenhua WANG）
Author-email: i@jackwish.net
License: Apache License 2.0
Project-URL: Bug Reports, https://github.com/jackwish/shrub/issues
Project-URL: Source, https://github.com/jackwish/shrub
Keywords: tflite,onnx,tvm,deep-learning
Platform: UNKNOWN
Classifier: Development Status :: 2 - Pre-Alpha
Classifier: Programming Language :: Python :: 3
Classifier: Programming Language :: Python :: 3.5
Classifier: Programming Language :: Python :: 3.6
Classifier: Programming Language :: Python :: 3.7
Classifier: Programming Language :: Python :: 3.8
Classifier: Environment :: Console
Classifier: Intended Audience :: Developers
Classifier: License :: OSI Approved :: Apache Software License
Classifier: Natural Language :: English
Classifier: Operating System :: OS Independent
Classifier: Topic :: Scientific/Engineering :: Artificial Intelligence
Requires-Python: >=3.5.*, <4
Requires-Dist: numpy
Requires-Dist: onnx
Requires-Dist: onnxruntime
Requires-Dist: pillow
Requires-Dist: tensorflow (>=2.0.0)
Requires-Dist: tflite
